[
  {
    "user_id": 165,
    "email": "user165@example.com",
    "created_at": "2025-11-12T00:00:00+00:00",
    "country": "GB"
  },
  {
    "user_id": 166,
    "email": "user166@example.com",
    "created_at": "2025-11-12T00:00:00+00:00",
    "country": "DE"
  },
  {
    "user_id": 167,
    "email": "user167@example.com",
    "created_at": "2025-11-12T00:00:00+00:00",
    "country": "NL"
  },
  {
    "user_id": 168,
    "email": "user168@example.com",
    "created_at": "2025-11-12T00:00:00+00:00",
    "country": "IT"
  },
  {
    "user_id": 169,
    "email": "user169@example.com",
    "created_at": "2025-11-12T00:00:00+00:00",
    "country": "NL"
  },
  {
    "user_id": 170,
    "email": "user170@example.com",
    "created_at": "2025-11-12T00:00:00+00:00",
    "country": "FR"
  },
  {
    "user_id": 171,
    "email": "user171@example.com",
    "created_at": "2025-11-12T00:00:00+00:00",
    "country": "DE"
  },
  {
    "user_id": 172,
    "email": "user172@example.com",
    "created_at": "2025-11-12T00:00:00+00:00",
    "country": "US"
  },
  {
    "user_id": 173,
    "email": "user173@example.com",
    "created_at": "2025-11-12T00:00:00+00:00",
    "country": "CA"
  },
  {
    "user_id": 174,
    "email": "user174@example.com",
    "created_at": "2025-11-12T00:00:00+00:00",
    "country": "ES"
  }
]